time_buddy.py
time_buddy-1.2.0.dist-info/licenses/LICENSE
time_buddy-1.2.0.dist-info/METADATA
time_buddy-1.2.0.dist-info/WHEEL
time_buddy-1.2.0.dist-info/entry_points.txt
time_buddy-1.2.0.dist-info/top_level.txt
time_buddy-1.2.0.dist-info/RECORD
