Metadata-Version: 2.4
Name: time-buddy
Version: 1.2.0
Summary: A simple to use time tracking CLI for macOS.
License-Expression: MIT
Project-URL: Homepage, https://github.com/alen-z/time-buddy
Project-URL: Repository, https://github.com/alen-z/time-buddy
Project-URL: Issues, https://github.com/alen-z/time-buddy/issues
Keywords: time-tracking,macos,cli,screen-time,productivity
Classifier: Operating System :: MacOS
Classifier: Environment :: Console
Classifier: Topic :: Utilities
Requires-Python: >=3.7
License-File: LICENSE
Requires-Dist: tzlocal
Requires-Dist: halo
Requires-Dist: colorama
Requires-Dist: fpdf2
Dynamic: license-file
